compliance_suite/__init__.py
compliance_suite/cli.py
compliance_suite/info_algorithms.py
compliance_suite/metadata_algorithms.py
compliance_suite/report_server.py
compliance_suite/sequence_algorithms.py
compliance_suite/test_runner.py
compliance_suite/tests.py
compliance_suite/utils.py
compliance_suite/sequences/I.faa
compliance_suite/sequences/NC.faa
compliance_suite/sequences/VI.faa
compliance_suite/sequences/checksums.json
compliance_suite/web/index.css
compliance_suite/web/index.html
compliance_suite/web/index.js
compliance_suite/web/jquery.js
compliance_suite/web/jquery.jsonPresenter.css
compliance_suite/web/jquery.jsonPresenter.js
compliance_suite/web/temp_result.json
refget_compliance-1.2.6.dist-info/METADATA
refget_compliance-1.2.6.dist-info/RECORD
refget_compliance-1.2.6.dist-info/WHEEL
refget_compliance-1.2.6.dist-info/entry_points.txt
refget_compliance-1.2.6.dist-info/top_level.txt
