Metadata-Version: 2.1
Name: refget-compliance
Version: 1.2.6
Summary: A compliance utility reporting system for refget server implementations
Home-page: https://github.com/ga4gh/refget-compliance-suite
Author: Somesh Chaturvedi
Author-email: somesh.08.96@gmail.com
License: UNKNOWN
Platform: UNKNOWN
Classifier: Programming Language :: Python :: 3
Classifier: License :: OSI Approved :: Apache Software License
Classifier: Operating System :: OS Independent
Requires-Dist: requests
Requires-Dist: click
